Metadata-Version: 1.1
Name: Oto
Version: 0.0.1
Summary: Standardize communication between the different layers of an application.
Home-page: https://github.com/xethorn/oto
Author: Michael Ortali
Author-email: github@xethorn.net
License: MIT
Platform: UNKNOWN
Classifier: Development Status :: Alpha
Classifier: Programming Language :: Python :: 3.3
Classifier: Programming Language :: Python :: 3.4
Classifier: Programming Language :: Python :: 3.5
